{
  "project_info": {
    "project_number": "484284607211",
    "project_id": "azkar-66e51",
    "storage_bucket": "azkar-66e51.appspot.com"
  },
  "client": [
    {
      "client_info": {
        "mobilesdk_app_id": "1:484284607211:android:85de45d9e7cced4d9cacae",
        "android_client_info": {
          "package_name": "com.ajwa.azkar"
        }
      },
      "oauth_client": [
        {
          "client_id": "484284607211-5jfh093tdelfdu183tdhog9niv6s0trh.apps.googleusercontent.com",
          "client_type": 3
        }
      ],
      "api_key": [
        {
          "current_key": "AIzaSyBVkbVsSFuGWZovkiXb2XVWhSIN0w_EOlw"
        }
      ],
      "services": {
        "appinvite_service": {
          "other_platform_oauth_client": [
            {
              "client_id": "484284607211-5jfh093tdelfdu183tdhog9niv6s0trh.apps.googleusercontent.com",
              "client_type": 3
            }
          ]
        }
      }
    }
  ],
  "configuration_version": "1"
}